<annotation>
  <folder>fullimages2017</folder>
  <filename>58</filename>
  <path>58.jpg</path>
  <source>
    <database>Unknown</database>
  </source>
  <size>
    <width>1024</width>
    <height>768</height>
    <depth>3</depth>
  </size>
  <segmented>0</segmented>
  <object>
    <name>إيدبل</name>
    <pose>Unspecified</pose>
    <truncated>0</truncated>
    <difficult>0</difficult>
    <bndbox>
      <xmin>518</xmin>
      <ymin>5</ymin>
      <xmax>693</xmax>
      <ymax>88</ymax>
    </bndbox>
  </object>
  <object>
    <name>أرينجمنتس</name>
    <pose>Unspecified</pose>
    <truncated>0</truncated>
    <difficult>0</difficult>
    <bndbox>
      <xmin>463</xmin>
      <ymin>70</ymin>
      <xmax>773</xmax>
      <ymax>155</ymax>
    </bndbox>
  </object>
  <object>
    <name>Edible</name>
    <pose>Unspecified</pose>
    <truncated>0</truncated>
    <difficult>0</difficult>
    <bndbox>
      <xmin>106</xmin>
      <ymin>6</ymin>
      <xmax>265</xmax>
      <ymax>80</ymax>
    </bndbox>
  </object>
  <object>
    <name>arrangements</name>
    <pose>Unspecified</pose>
    <truncated>0</truncated>
    <difficult>0</difficult>
    <bndbox>
      <xmin>28</xmin>
      <ymin>58</ymin>
      <xmax>343</xmax>
      <ymax>144</ymax>
    </bndbox>
  </object>
</annotation>
