<annotation>
  <folder>malayalam</folder>
  <filename>116</filename>
  <path>/home/minesh/RealSceneImages/self/malayalam/116.jpg</path>
  <source>
    <database>Unknown</database>
  </source>
  <size>
    <width>3456</width>
    <height>2304</height>
    <depth>3</depth>
  </size>
  <segmented>0</segmented>
  <object>
    <name>മൻമോഹൻ</name>
    <pose>Unspecified</pose>
    <truncated>0</truncated>
    <difficult>0</difficult>
    <bndbox>
      <xmin>249</xmin>
      <ymin>1378</ymin>
      <xmax>2080</xmax>
      <ymax>1805</ymax>
    </bndbox>
  </object>
  <object>
    <name>ബംഗ്ലാവു്</name>
    <pose>Unspecified</pose>
    <truncated>0</truncated>
    <difficult>0</difficult>
    <bndbox>
      <xmin>2107</xmin>
      <ymin>1359</ymin>
      <xmax>3249</xmax>
      <ymax>1944</ymax>
    </bndbox>
  </object>
</annotation>
